alpcom_api/__init__.py
alpcom_api/apis.py
alpcom_api/cache.py
alpcom_api/clients.py
alpcom_api/dto.py
alpcom_api/errors.py
alpcom_api/factories.py
alpcom_api/ws.py
alpcom_api-1.0.3.dist-info/LICENSE
alpcom_api-1.0.3.dist-info/METADATA
alpcom_api-1.0.3.dist-info/WHEEL
alpcom_api-1.0.3.dist-info/top_level.txt
alpcom_api-1.0.3.dist-info/RECORD
