Metadata-Version: 2.1
Name: alpcom-api
Version: 1.0.3
Summary: ALP.com API Python
Author: ALP.com
License: MIT
License-File: LICENSE
Requires-Dist: requests (==2.31.0)
Requires-Dist: pydantic (==2.1.1)
Requires-Dist: pyjwt (==2.8.0)
Requires-Dist: websockets (==11.0.3)
